names/__init__.py
names/admin.py
names/apps.py
names/conf.py
names/fields.py
names/mixins.py
names/models.py
names/migrations/0001_initial.py
names/migrations/__init__.py
django_names-1.0.5.dist-info/LICENSE.md
django_names-1.0.5.dist-info/METADATA
django_names-1.0.5.dist-info/WHEEL
django_names-1.0.5.dist-info/top_level.txt
django_names-1.0.5.dist-info/RECORD
