Metadata-Version: 2.1
Name: django-names
Version: 1.0.5
Summary: Names is a reusable app for Django that provides mixins, models and form fields to store a full name and its individual components.
Home-page: https://github.com/jcp/django-names
Author: James C. Palmer
Author-email: me@jcp.io
License: BSD 3-Clause
Platform: UNKNOWN
Classifier: Development Status :: 5 - Production/Stable
Classifier: Environment :: Web Environment
Classifier: Framework :: Django
Classifier: Framework :: Django :: 1.11
Classifier: Framework :: Django :: 2.0
Classifier: Framework :: Django :: 2.1
Classifier: Framework :: Django :: 2.2
Classifier: Intended Audience :: Developers
Classifier: License :: OSI Approved :: BSD License
Classifier: Operating System :: OS Independent
Classifier: Programming Language :: Python
Classifier: Programming Language :: Python :: 3
Classifier: Programming Language :: Python :: 3.6
Classifier: Programming Language :: Python :: 3.7
Requires-Python: >=3.6
Requires-Dist: Django (>=1.11)
Requires-Dist: nameparser (>=1.0.4)
